jupyt/__init__.py
jupyt/_version.py
jupyt-0.4.1.data/data/share/jupyter/labextensions/jupyt/build_log.json
jupyt-0.4.1.data/data/share/jupyter/labextensions/jupyt/package.json
jupyt-0.4.1.data/data/share/jupyter/labextensions/jupyt/schemas/jupyt/package.json.orig
jupyt-0.4.1.data/data/share/jupyter/labextensions/jupyt/schemas/jupyt/plugin.json
jupyt-0.4.1.data/data/share/jupyter/labextensions/jupyt/static/lib_index_js.00593babb69cfc0d8ea8.js
jupyt-0.4.1.data/data/share/jupyter/labextensions/jupyt/static/lib_index_js.00593babb69cfc0d8ea8.js.map
jupyt-0.4.1.data/data/share/jupyter/labextensions/jupyt/static/lib_index_js.0177dca35202958e1a9d.js
jupyt-0.4.1.data/data/share/jupyter/labextensions/jupyt/static/lib_index_js.0177dca35202958e1a9d.js.map
jupyt-0.4.1.data/data/share/jupyter/labextensions/jupyt/static/lib_index_js.01e6fae12c2ca55308b4.js
jupyt-0.4.1.data/data/share/jupyter/labextensions/jupyt/static/lib_index_js.01e6fae12c2ca55308b4.js.map
jupyt-0.4.1.data/data/share/jupyter/labextensions/jupyt/static/lib_index_js.0224883b2c333350c82b.js
jupyt-0.4.1.data/data/share/jupyter/labextensions/jupyt/static/lib_index_js.0224883b2c333350c82b.js.map
jupyt-0.4.1.data/data/share/jupyter/labextensions/jupyt/static/lib_index_js.0308ecb5568897bf2661.js
jupyt-0.4.1.data/data/share/jupyter/labextensions/jupyt/static/lib_index_js.0308ecb5568897bf2661.js.map
jupyt-0.4.1.data/data/share/jupyter/labextensions/jupyt/static/lib_index_js.078d936435a8dbae06f8.js
jupyt-0.4.1.data/data/share/jupyter/labextensions/jupyt/static/lib_index_js.078d936435a8dbae06f8.js.map
jupyt-0.4.1.data/data/share/jupyter/labextensions/jupyt/static/lib_index_js.09bac2f075636b175d86.js
jupyt-0.4.1.data/data/share/jupyter/labextensions/jupyt/static/lib_index_js.09bac2f075636b175d86.js.map
jupyt-0.4.1.data/data/share/jupyter/labextensions/jupyt/static/lib_index_js.0beddf2759b94f634b39.js
jupyt-0.4.1.data/data/share/jupyter/labextensions/jupyt/static/lib_index_js.0beddf2759b94f634b39.js.map
jupyt-0.4.1.dist-info/METADATA
jupyt-0.4.1.dist-info/WHEEL
jupyt-0.4.1.dist-info/licenses/LICENSE
jupyt-0.4.1.dist-info/RECORD
