Metadata-Version: 2.4
Name: jupyt
Version: 0.4.1
Summary: Making ipynb cooler
Project-URL: Homepage, https://ipynb.ai
Project-URL: Bug Tracker, https://ipynb.ai/
Project-URL: Repository, https://ipynb.ai.git
Author-email: Rajmeet <rajmeetchandok@gmail.com>
License: Copyright (c) 2024-2025, Jupyt
License-File: LICENSE
Keywords: jupyter,jupyterlab,jupyterlab-extension
Classifier: Framework :: Jupyter
Classifier: Framework :: Jupyter :: JupyterLab
Classifier: Framework :: Jupyter :: JupyterLab :: 4
Classifier: Framework :: Jupyter :: JupyterLab :: Extensions
Classifier: Framework :: Jupyter :: JupyterLab :: Extensions :: Prebuilt
Classifier: License :: OSI Approved :: BSD License
Classifier: Programming Language :: Python
Classifier: Programming Language :: Python :: 3
Classifier: Programming Language :: Python :: 3.9
Classifier: Programming Language :: Python :: 3.10
Classifier: Programming Language :: Python :: 3.11
Classifier: Programming Language :: Python :: 3.12
Classifier: Programming Language :: Python :: 3.13
Requires-Python: >=3.9
